tadau/__init__.py
tadau/measurement_protocol.py
tadau/measurement_protocol_test.py
tadau/version.py
tadau-1.0.8.dist-info/METADATA
tadau-1.0.8.dist-info/WHEEL
tadau-1.0.8.dist-info/top_level.txt
tadau-1.0.8.dist-info/RECORD
