Metadata-Version: 2.2
Name: tadau
Version: 1.0.8
Summary: Tadau: TrAck Downloads, Adoption and Usage of external solutions.
Home-page: https://github.com/google-marketing-solutions/tadau
Author: Google Inc.
Author-email: gps-tadau+copybara@google.com
License: Apache 2.0
Keywords: tadau track google marketing solutions
Classifier: License :: OSI Approved :: Apache Software License
Requires-Dist: absl-py
Requires-Dist: requests
Requires-Dist: pyyaml
Dynamic: author
Dynamic: author-email
Dynamic: classifier
Dynamic: description
Dynamic: description-content-type
Dynamic: home-page
Dynamic: keywords
Dynamic: license
Dynamic: requires-dist
Dynamic: summary
